MRISeg/MRISeg.py
MRISeg/__init__.py
MRISeg-0.0.1.dist-info/LICENSE
MRISeg-0.0.1.dist-info/METADATA
MRISeg-0.0.1.dist-info/WHEEL
MRISeg-0.0.1.dist-info/entry_points.txt
MRISeg-0.0.1.dist-info/top_level.txt
MRISeg-0.0.1.dist-info/RECORD
